{
  "기본정보": {
    "교과목명": "통신공학",
    "분반": "1",
    "담당교수명": "최재호",
    "학점": "3",
    "연락처": "270-2415",
    "교과목 코드": "0000105881",
    "요일/시간": "화 6-A,화 6-B,화 7-A,화 7-B,목 8-A,목 8-B",
    "E-mail": "wave@jbnu.edu",
    "교과목 구분": "전공선택",
    "연구실": "430",
    "학과/학년": "전자공학부 3",
    "강의실": "전주:공과대학 7호관 112",
    "상담가능시간": "Anytime by appointment",
    "수업목표": "Studies on analog communications theory and systems.",
    "직전강의평가\n및\nCQI반영사항": "Students need to have fulfilled prerequisite courses, which are Signals and Systems and \nBasic Circuit 1.  \nStudents should be also ready for the English lecture.",
    "구분": "소통역량",
    "창의역량": "인성역량",
    "실무역량": "도전역량",
    "문화역량": "합계",
    "비율(%)": "40",
    "20": "10",
    "0": "100",
    "주교재": "Communication systems  -Carlson-McGraw Hill-2010",
    "저자": "Carlson",
    "출판사": "McGraw Hill",
    "출판년도": "2010",
    "교재언어": "영어",
    "강의언어": "영어",
    "권장 선수과목": "Signals and Systems; Circuits 1",
    "권장 후수과목": "DA",
    "수업방식\n(복수가능√)": "강의",
    "발표/토론": "수업태도",
    "플립러닝": "LMS활용",
    "실험실습": "기타",
    "√": "√",
    "기말": "출석",
    "과제물": "안전교육",
    "25%": "50%",
    "10%": "15%",
    "0%": "0%",
    "평가참고사항": "."
  },
  "평가방법": {
    "상대평가 비율": "A(%)",
    "A+B(%)": "C이하(%)",
    "40": "80",
    "20": "100%",
    "참고\n사항": "* 장애학생 교수학습지원 사항",
    "- 강의": "√",
    "강의 파일, 자료 등 제공": "좌석배치(지정좌석) 조정",
    "- 과제": "√",
    "과제 제출기한 연장": "대안적 과제 제시",
    "- 평가": "√",
    "시험시간 연장": "평가방법 조정(대독, 구두응답, 도우미 대필 답안작성 등)",
    "주별": "수업목표",
    "수업내용": "수업방식",
    "자료, 과제 및\n기타 참고사항": "수업방식별시간",
    "온라인": "오프라인",
    "1주": "Introduction",
    "Course syllabus and survey": "lectures",
    "중간": "기말",
    "출석": "과제물",
    "안전교육": "발표/토론",
    "수업태도": "기타",
    "평가참고사항": "."
  },
  "핵심역량": {}
}